{
    "resultType": "matrix",
    "result": [
        {
            "metric": {
                "DstK8S_Namespace": "netobserv",
                "SrcK8S_Namespace": "openshift-console"
            },
            "values": [
                [
                    1673037555,
                    "317.6"
                ],
                [
                    1673037570,
                    "2075.133333333333"
                ],
                [
                    1673037585,
                    "1775.1333333333334"
                ],
                [
                    1673037600,
                    "57.6"
                ],
                [
                    1673037615,
                    "40"
                ],
                [
                    1673037675,
                    "321.6666666666667"
                ],
                [
                    1673037690,
                    "326.06666666666666"
                ],
                [
                    1673037705,
                    "19.2"
                ],
                [
                    1673037720,
                    "14.8"
                ]
            ]
        },
        {
            "metric": {
                "DstK8S_Namespace": "netobserv",
                "SrcK8S_Namespace": "openshift-dns"
            },
            "values": [
                [
                    1673037555,
                    "1357.9"
                ],
                [
                    1673037570,
                    "1651.5"
                ],
                [
                    1673037585,
                    "1614.8000000000002"
                ],
                [
                    1673037600,
                    "1321.2"
                ],
                [
                    1673037615,
                    "1321.2"
                ],
                [
                    1673037630,
                    "1321.2"
                ],
                [
                    1673037645,
                    "1321.2"
                ],
                [
                    1673037660,
                    "1394.6000000000001"
                ],
                [
                    1673037675,
                    "1431.3"
                ],
                [
                    1673037690,
                    "1357.9"
                ],
                [
                    1673037705,
                    "1321.2"
                ],
                [
                    1673037720,
                    "1321.2"
                ],
                [
                    1673037735,
                    "1321.2"
                ],
                [
                    1673037750,
                    "1321.2"
                ],
                [
                    1673037765,
                    "1321.2"
                ],
                [
                    1673037780,
                    "1247.8"
                ],
                [
                    1673037795,
                    "1284.5"
                ],
                [
                    1673037810,
                    "1357.9"
                ],
                [
                    1673037825,
                    "1321.2"
                ],
                [
                    1673037840,
                    "1321.2"
                ],
                [
                    1673037855,
                    "1321.2"
                ]
            ]
        },
        {
            "metric": {
                "DstK8S_Namespace": "default",
                "SrcK8S_Namespace": "netobserv"
            },
            "values": [
                [
                    1673037555,
                    "1872.5"
                ],
                [
                    1673037570,
                    "1860.0333333333333"
                ],
                [
                    1673037585,
                    "1574.0666666666666"
                ],
                [
                    1673037600,
                    "1605.4666666666667"
                ],
                [
                    1673037615,
                    "1582.4333333333332"
                ],
                [
                    1673037630,
                    "1838.8666666666666"
                ],
                [
                    1673037645,
                    "1870.8666666666666"
                ],
                [
                    1673037660,
                    "1699.3999999999999"
                ],
                [
                    1673037675,
                    "1596.4666666666665"
                ],
                [
                    1673037690,
                    "1412.1333333333334"
                ],
                [
                    1673037705,
                    "1593.2"
                ],
                [
                    1673037720,
                    "1604.1999999999998"
                ],
                [
                    1673037735,
                    "1517.8333333333333"
                ],
                [
                    1673037750,
                    "1509.0333333333333"
                ],
                [
                    1673037765,
                    "1554.2"
                ],
                [
                    1673037780,
                    "1553.2666666666667"
                ],
                [
                    1673037795,
                    "1510.6999999999998"
                ],
                [
                    1673037810,
                    "1829.0333333333333"
                ],
                [
                    1673037825,
                    "2065.6"
                ],
                [
                    1673037840,
                    "2116.5"
                ],
                [
                    1673037855,
                    "1839.9666666666667"
                ]
            ]
        },
        {
            "metric": {
                "DstK8S_Namespace": "netobserv",
                "SrcK8S_Namespace": "netobserv"
            },
            "values": [
                [
                    1673037555,
                    "561096.2333333334"
                ],
                [
                    1673037570,
                    "572149.5666666667"
                ],
                [
                    1673037585,
                    "557498.7999999999"
                ],
                [
                    1673037600,
                    "543956.6333333333"
                ],
                [
                    1673037615,
                    "568973"
                ],
                [
                    1673037630,
                    "587434.5"
                ],
                [
                    1673037645,
                    "560446.6333333333"
                ],
                [
                    1673037660,
                    "524709.9666666667"
                ],
                [
                    1673037675,
                    "520388.4666666667"
                ],
                [
                    1673037690,
                    "515696.9666666667"
                ],
                [
                    1673037705,
                    "517222.3"
                ],
                [
                    1673037720,
                    "525105.4"
                ],
                [
                    1673037735,
                    "530506.4666666667"
                ],
                [
                    1673037750,
                    "526340.1333333333"
                ],
                [
                    1673037765,
                    "517303.1666666667"
                ],
                [
                    1673037780,
                    "540779.7999999999"
                ],
                [
                    1673037795,
                    "792445.2000000001"
                ],
                [
                    1673037810,
                    "804384.7666666666"
                ],
                [
                    1673037825,
                    "556054.0666666667"
                ],
                [
                    1673037840,
                    "527157"
                ],
                [
                    1673037855,
                    "523783.8"
                ]
            ]
        },
        {
            "metric": {
                "DstK8S_Namespace": "openshift-console",
                "SrcK8S_Namespace": "netobserv"
            },
            "values": [
                [
                    1673037555,
                    "6219.6"
                ],
                [
                    1673037570,
                    "371966.2"
                ],
                [
                    1673037585,
                    "365764.2"
                ],
                [
                    1673037600,
                    "70.4"
                ],
                [
                    1673037615,
                    "52.8"
                ],
                [
                    1673037675,
                    "848.0666666666667"
                ],
                [
                    1673037690,
                    "852.4666666666667"
                ],
                [
                    1673037705,
                    "22"
                ],
                [
                    1673037720,
                    "17.6"
                ]
            ]
        },
        {
            "metric": {
                "DstK8S_Namespace": "openshift-dns",
                "SrcK8S_Namespace": "netobserv"
            },
            "values": [
                [
                    1673037555,
                    "725.2"
                ],
                [
                    1673037570,
                    "882"
                ],
                [
                    1673037585,
                    "862.4000000000001"
                ],
                [
                    1673037600,
                    "705.6"
                ],
                [
                    1673037615,
                    "705.6"
                ],
                [
                    1673037630,
                    "705.6"
                ],
                [
                    1673037645,
                    "705.6"
                ],
                [
                    1673037660,
                    "744.8000000000001"
                ],
                [
                    1673037675,
                    "764.4"
                ],
                [
                    1673037690,
                    "725.2"
                ],
                [
                    1673037705,
                    "705.6"
                ],
                [
                    1673037720,
                    "705.6"
                ],
                [
                    1673037735,
                    "705.6"
                ],
                [
                    1673037750,
                    "705.6"
                ],
                [
                    1673037765,
                    "705.6"
                ],
                [
                    1673037780,
                    "666.4"
                ],
                [
                    1673037795,
                    "686"
                ],
                [
                    1673037810,
                    "725.2"
                ],
                [
                    1673037825,
                    "705.6"
                ],
                [
                    1673037840,
                    "705.6"
                ],
                [
                    1673037855,
                    "705.6"
                ]
            ]
        },
        {
            "metric": {
                "SrcK8S_Namespace": "netobserv"
            },
            "values": [
                [
                    1673037555,
                    "1144.3333333333333"
                ],
                [
                    1673037570,
                    "1143.3333333333335"
                ],
                [
                    1673037585,
                    "1060.8"
                ],
                [
                    1673037600,
                    "1031.3000000000002"
                ],
                [
                    1673037615,
                    "1046.6666666666667"
                ],
                [
                    1673037630,
                    "1067.5333333333333"
                ],
                [
                    1673037645,
                    "1064.9333333333334"
                ],
                [
                    1673037660,
                    "1084.6"
                ],
                [
                    1673037675,
                    "1038.3"
                ],
                [
                    1673037690,
                    "992.1666666666667"
                ],
                [
                    1673037705,
                    "1010.2"
                ],
                [
                    1673037720,
                    "984.9"
                ],
                [
                    1673037735,
                    "1029.1333333333334"
                ],
                [
                    1673037750,
                    "1062.3333333333333"
                ],
                [
                    1673037765,
                    "1035.6999999999998"
                ],
                [
                    1673037780,
                    "965.9666666666666"
                ],
                [
                    1673037795,
                    "1001.2333333333333"
                ],
                [
                    1673037810,
                    "1091.3333333333335"
                ],
                [
                    1673037825,
                    "1136"
                ],
                [
                    1673037840,
                    "1210.1333333333334"
                ],
                [
                    1673037855,
                    "1124.5"
                ]
            ]
        }
    ],
    "stats": {
        "numQueries": 2,
        "limitReached": false,
        "queriesStats": [
            {
                "ingester": {
                    "store": {
                        "chunk": {
                            "compressedBytes": 1042626,
                            "decompressedBytes": 4678936,
                            "decompressedLines": 6625,
                            "headChunkBytes": 379711,
                            "headChunkLines": 556,
                            "totalDuplicates": 1937
                        },
                        "chunksDownloadTime": 1557743,
                        "totalChunksDownloaded": 4,
                        "totalChunksRef": 4
                    },
                    "totalBatches": 16,
                    "totalChunksMatched": 13,
                    "totalLinesSent": 3030,
                    "totalReached": 96
                },
                "querier": {
                    "store": {
                        "chunk": {
                            "compressedBytes": 0,
                            "decompressedBytes": 0,
                            "decompressedLines": 0,
                            "headChunkBytes": 0,
                            "headChunkLines": 0,
                            "totalDuplicates": 0
                        },
                        "chunksDownloadTime": 0,
                        "totalChunksDownloaded": 0,
                        "totalChunksRef": 0
                    }
                },
                "summary": {
                    "bytesProcessedPerSecond": 32095925,
                    "execTime": 0.157610253,
                    "linesProcessedPerSecond": 45561,
                    "queueTime": 3.529993701,
                    "subqueries": 6,
                    "totalBytesProcessed": 5058647,
                    "totalEntriesReturned": 2,
                    "totalLinesProcessed": 7181
                }
            },
            {
                "ingester": {
                    "store": {
                        "chunk": {
                            "compressedBytes": 1554485,
                            "decompressedBytes": 5804022,
                            "decompressedLines": 9087,
                            "headChunkBytes": 2008920,
                            "headChunkLines": 3257,
                            "totalDuplicates": 0
                        },
                        "chunksDownloadTime": 0,
                        "totalChunksDownloaded": 0,
                        "totalChunksRef": 0
                    },
                    "totalBatches": 62,
                    "totalChunksMatched": 94,
                    "totalLinesSent": 6183,
                    "totalReached": 96
                },
                "querier": {
                    "store": {
                        "chunk": {
                            "compressedBytes": 0,
                            "decompressedBytes": 0,
                            "decompressedLines": 0,
                            "headChunkBytes": 0,
                            "headChunkLines": 0,
                            "totalDuplicates": 0
                        },
                        "chunksDownloadTime": 0,
                        "totalChunksDownloaded": 0,
                        "totalChunksRef": 0
                    }
                },
                "summary": {
                    "bytesProcessedPerSecond": 48001410,
                    "execTime": 0.162764843,
                    "linesProcessedPerSecond": 75839,
                    "queueTime": 3.601398724,
                    "subqueries": 6,
                    "totalBytesProcessed": 7812942,
                    "totalEntriesReturned": 5,
                    "totalLinesProcessed": 12344
                }
            }
        ]
    },
    "isMock": true
}